pytorchPipline/BenchMark.py
pytorchPipline/Pipline.py
pytorchPipline/__init__.py
pytorch_pipline-0.2.4.dist-info/METADATA
pytorch_pipline-0.2.4.dist-info/WHEEL
pytorch_pipline-0.2.4.dist-info/top_level.txt
pytorch_pipline-0.2.4.dist-info/RECORD
