Metadata-Version: 2.1
Name: pytorch-pipline
Version: 0.2.4
Summary: Making pytorch training easier
Author: Charlie Huang
Author-email: <charliehuang09@gmail.com>
Keywords: python
Classifier: Development Status :: 1 - Planning
Classifier: Intended Audience :: Developers
Classifier: Programming Language :: Python :: 3
Classifier: Operating System :: Unix
Classifier: Operating System :: MacOS :: MacOS X
Classifier: Operating System :: Microsoft :: Windows
Requires-Dist: torchvision
Requires-Dist: torch
Requires-Dist: numpy
Requires-Dist: tqdm
